odoo/addons/stock_packaging_calculator/README.rst
odoo/addons/stock_packaging_calculator/__init__.py
odoo/addons/stock_packaging_calculator/__manifest__.py
odoo/addons/stock_packaging_calculator/i18n/it.po
odoo/addons/stock_packaging_calculator/i18n/stock_packaging_calculator.pot
odoo/addons/stock_packaging_calculator/readme/CONTRIBUTORS.md
odoo/addons/stock_packaging_calculator/readme/DESCRIPTION.md
odoo/addons/stock_packaging_calculator/static/description/icon.png
odoo/addons/stock_packaging_calculator/static/description/index.html
odoo_addon_stock_packaging_calculator-18.0.2.0.0.1.dist-info/METADATA
odoo_addon_stock_packaging_calculator-18.0.2.0.0.1.dist-info/WHEEL
odoo_addon_stock_packaging_calculator-18.0.2.0.0.1.dist-info/top_level.txt
odoo_addon_stock_packaging_calculator-18.0.2.0.0.1.dist-info/RECORD
