Metadata-Version: 2.1
Name: odoo-addon-stock_packaging_calculator
Version: 18.0.2.0.0.1
Requires-Python: >=3.10
Requires-Dist: odoo-addon-product_packaging_calculator==18.0.*
Requires-Dist: odoo==18.0.*
Requires-Dist: openupgradelib
Summary: Compute product quantity to pick by packaging
Home-page: https://github.com/OCA/stock-logistics-warehouse
License: LGPL-3
Author: Camptocamp, Odoo Community Association (OCA)
Author-email: support@odoo-community.org
Classifier: Programming Language :: Python
Classifier: Framework :: Odoo
Classifier: Framework :: Odoo :: 18.0
Classifier: License :: OSI Approved :: GNU Lesser General Public License v3 (LGPLv3)
Classifier: Development Status :: 4 - Beta
